[
  {
    "Code": "ABA",
    "Name": "Abando",
    "Lines": ["L1", "L2"],
    "Platform1": ["MOY"],
    "Platform2": ["CAV"]
  },
  {
    "Code": "ABT",
    "Name": "Abatxolo",
    "Lines": ["L2"],
    "Platform1": ["POR"],
    "Platform2": ["SES"]
  },
  {
    "Code": "AIB",
    "Name": "Aiboa",
    "Lines": ["L1"],
    "Platform1": ["ALG"],
    "Platform2": ["NEG"]
  },
  {
    "Code": "ALG",
    "Name": "Algorta",
    "Lines": ["L1"],
    "Platform1": ["BID"],
    "Platform2": ["NEG"]
  },
  {
    "Code": "ANS",
    "Name": "Ansio",
    "Lines": ["L2"],
    "Platform1": ["BAR"],
    "Platform2": ["SIN"]
  },
  {
    "Code": "ARE",
    "Name": "Areeta",
    "Lines": ["L1"],
    "Platform1": ["GOB"],
    "Platform2": ["LAM"]
  },
  {
    "Code": "ARZ",
    "Name": "Ariz",
    "Lines": ["L2"],
    "Platform1": ["BSR"],
    "Platform2": ["ETX"]
  },
  {
    "Code": "AST",
    "Name": "Astrabudua",
    "Lines": ["L1"],
    "Platform1": ["LEI"],
    "Platform2": ["ERA"]
  },
  {
    "Code": "BAG",
    "Name": "Bagatza",
    "Lines": ["L2"],
    "Platform1": ["URB"],
    "Platform2": ["BAG"]
  },
  {
    "Code": "BAR",
    "Name": "Barakaldo",
    "Lines": ["L2"],
    "Platform1": ["BAG"],
    "Platform2": ["ANS"]
  },
  {
    "Code": "BAS",
    "Name": "Basarrate",
    "Lines": ["L1", "L2"],
    "Platform1": ["SAN"],
    "Platform2": ["BOL"]
  },
  {
    "Code": "BSR",
    "Name": "Basauri",
    "Lines": ["L2"],
    "Platform1": [],
    "Platform2": ["ARZ"]
  },
  {
    "Code": "BER",
    "Name": "Berango",
    "Lines": ["L1"],
    "Platform1": ["SOP"],
    "Platform2": ["IBB"]
  },
  {
    "Code": "BID",
    "Name": "Bidezabal",
    "Lines": ["L1"],
    "Platform1": ["IBB"],
    "Platform2": ["ALG"]
  },
  {
    "Code": "BOL",
    "Name": "Bolueta",
    "Lines": ["L1", "L2"],
    "Platform1": ["BAS"],
    "Platform2": ["ETX"]
  },
  {
    "Code": "DEU",
    "Name": "Deustu",
    "Lines": ["L1", "L2"],
    "Platform1": ["SAR"],
    "Platform2": ["SAM"]
  },
  {
    "Code": "ERA",
    "Name": "Erandio",
    "Lines": ["L1"],
    "Platform1": ["AST"],
    "Platform2": ["LUT"]
  },
  {
    "Code": "ETX",
    "Name": "Etxebarri",
    "Lines": ["L1", "L2"],
    "Platform1": ["BOL"],
    "Platform2": ["ARZ"]
  },
  {
    "Code": "GOB",
    "Name": "Gobela",
    "Lines": ["L1"],
    "Platform1": ["NEG"],
    "Platform2": ["ARE"]
  },
  {
    "Code": "GUR",
    "Name": "Gurutzeta\/Cruces",
    "Lines": ["L2"],
    "Platform1": ["BAR"],
    "Platform2": ["ANS"]
  },
  {
    "Code": "IBB",
    "Name": "Ibarbengoa",
    "Lines": ["L1"],
    "Platform1": ["BER"],
    "Platform2": ["BID"]
  },
  {
    "Code": "IND",
    "Name": "Indautxu",
    "Lines": ["L1", "L2"],
    "Platform1": ["SAM"],
    "Platform2": ["MOY"]
  },
  {
    "Code": "KAB",
    "Name": "Kabiezes",
    "Lines": ["L2"],
    "Platform1": [],
    "Platform2": ["STZ"]
  },
  {
    "Code": "LAM",
    "Name": "Lamiako",
    "Lines": ["L1"],
    "Platform1": ["ARE"],
    "Platform2": ["LEI"]
  },
  {
    "Code": "LAR",
    "Name": "Larrabasterra",
    "Lines": ["L1"],
    "Platform1": ["SOP"],
    "Platform2": ["BER"]
  },
  {
    "Code": "LEI",
    "Name": "Leioa",
    "Lines": ["L1"],
    "Platform1": ["LAM"],
    "Platform2": ["AST"]
  },
  {
    "Code": "LUT",
    "Name": "Lutxana",
    "Lines": ["L1"],
    "Platform1": ["ERA"],
    "Platform2": ["SIN"]
  },
  {
    "Code": "MOY",
    "Name": "Moyua",
    "Lines": ["L1", "L2"],
    "Platform1": ["IND"],
    "Platform2": ["ABA"]
  },
  {
    "Code": "NEG",
    "Name": "Neguri",
    "Lines": ["L1"],
    "Platform1": ["AIB"],
    "Platform2": ["ARE"]
  },
  {
    "Code": "PEN",
    "Name": "Pe\u00f1ota",
    "Lines": ["L2"],
    "Platform1": ["STZ"],
    "Platform2": ["POR"]
  },
  {
    "Code": "PLE",
    "Name": "Plentzia",
    "Lines": ["L1"],
    "Platform1": [],
    "Platform2": ["URD"]
  },
  {
    "Code": "POR",
    "Name": "Portugalete",
    "Lines": ["L2"],
    "Platform1": ["PEN"],
    "Platform2": ["ABT"]
  },
  {
    "Code": "SAM",
    "Name": "Santimami\/San Mam\u00e9s",
    "Lines": ["L1", "L2"],
    "Platform1": ["DEU"],
    "Platform2": ["IND"]
  },
  {
    "Code": "SAN",
    "Name": "Santutxu",
    "Lines": ["L1", "L2"],
    "Platform1": ["CAV"],
    "Platform2": ["BAS"]
  },
  {
    "Code": "SAR",
    "Name": "Sarriko",
    "Lines": ["L1", "L2"],
    "Platform1": ["SIN"],
    "Platform2": ["DEU"]
  },
  {
    "Code": "SES",
    "Name": "Sestao",
    "Lines": ["L2"],
    "Platform1": ["ABT"],
    "Platform2": ["URB"]
  },
  {
    "Code": "SIN",
    "Name": "San Ignazio",
    "Lines": ["L1", "L2"],
    "Platform1": ["GUR", "LUT"],
    "Platform2": ["SAR"]
  },
  {
    "Code": "SOP",
    "Name": "Sopela",
    "Lines": ["L1"],
    "Platform1": ["URD"],
    "Platform2": ["LAR"]
  },
  {
    "Code": "STZ",
    "Name": "Santurtzi",
    "Lines": ["L2"],
    "Platform1": ["KAB"],
    "Platform2": ["PEN"]
  },
  {
    "Code": "URB",
    "Name": "Urbinaga",
    "Lines": ["L2"],
    "Platform1": ["BAG"],
    "Platform2": ["SIN"]
  },
  {
    "Code": "URD",
    "Name": "Urduliz",
    "Lines": ["L1"],
    "Platform1": ["PLE"],
    "Platform2": ["SOP"]
  },
  {
    "Code": "CAV",
    "Name": "Zazpikaleak\/Casco Viejo",
    "Lines": ["L1", "L2", "L3"],
    "Platform1": ["ABA"],
    "Platform2": ["SAN"]
  }
]